deeplake/__init__.py
labeldb/__init__.py
labeldb-0.0.1.dist-info/METADATA
labeldb-0.0.1.dist-info/WHEEL
labeldb-0.0.1.dist-info/top_level.txt
labeldb-0.0.1.dist-info/RECORD
