Metadata-Version: 2.1
Name: labeldb
Version: 0.0.1
Summary: LabelDB
Home-page: https://activeloop.ai
Author: Activeloop
Author-email: support@activeloop.ai
License: UNKNOWN
Platform: UNKNOWN
